{
  "start": {
    "button_1": {
      "callback": "main_menu",
      "command": 0
    },
    "button_2": {
      "callback": "main_menu",
      "command": 0
    },
    "button_3": {
      "callback": "main_menu",
      "command": 0
    },
    "button_4": {
      "callback": "main_menu",
      "command": 0
    }
  },
  "main_menu": {
    "button_1": {
      "callback": "main_information"
    },
    "button_2": {
      "callback": "support"
    },
    "button_3": {
      "callback": "frequent_questions"
    },
    "button_4": {
      "callback": "communication_with_manager",
      "command": 2
    },
    "button_5": {
      "callback": "main_menu"
    },
    "button_6": {
      "callback": "main_menu"
    },
    "button_7": {
      "callback": "drivers_handbook"
    }
  },
  "main_information": {
    "button_1": {
      "callback": "tariffs",
      "command": 2
    },
    "button_2": {
      "callback": "instruction_ontaxi_driver",
      "command": 2
    },
    "button_3": {
      "callback": "main_menu"
    }
  },
  "frequent_questions": {
    "button_1": {
      "callback": "filter_settings",
      "command": 2
    },
    "button_2": {
      "callback": "work_requirements",
      "command": 2
    },
    "button_3": {
      "callback": "order_cancellation",
      "command": 2
    },
    "button_4": {
      "callback": "how_to_register",
      "command": 2
    },
    "button_5": {
      "callback": "idle_in_orders",
      "command": 2
    },
    "button_6": {
      "callback": "main_menu"
    }
  },
  "support": {
    "button_1": {
      "callback": "contacts",
      "command": 2
    },
    "button_2": {
      "callback": "driver_chats",
      "command": 2
    },
    "button_3": {
      "callback": "leave_feedback",
      "command": 2
    },
    "button_4": {
      "callback": "main_menu"
    }
  },
  "drivers_handbook": {
    "button_1": {
      "callback": "guide_to_start_working"
    },
    "button_2": {
      "callback": "airport",
      "command": 2
    },
    "button_3": {
      "callback": "your_vehicle",
      "command": 2
    },
    "button_4": {
      "callback": "basic_laws_and_rules",
      "command": 2
    },
    "button_5": {
      "callback": "drivers_handbook"
    },
    "button_6": {
      "callback": "main_menu"
    }
  },
  "guide_to_start_working": {
    "button_1": {
      "callback": "joining_transport_company",
      "command": 2
    },
    "button_2": {
      "callback": "work_on_zivnostensky_list",
      "command": 2
    },
    "button_3": {
      "callback": "work_through_fleet",
      "command": 2
    },
    "button_4": {
      "callback": "main_menu"
    }
  }
}
